lmcache_vllm/__init__.py
lmcache_vllm/blend_adapter.py
lmcache_vllm/lmcache_utils.py
lmcache_vllm/script.py
lmcache_vllm/vllm_adapter.py
lmcache_vllm/vllm_injection.py
lmcache_vllm/attention/__init__.py
lmcache_vllm/attention/flash_attn.py
lmcache_vllm/experimental/__init__.py
lmcache_vllm/experimental/vllm_adapter.py
lmcache_vllm/models/__init__.py
lmcache_vllm/models/llama.py
lmcache_vllm/utils/__init__.py
lmcache_vllm/utils/positional_encoding.py
lmcache_vllm-0.6.2.3.dist-info/LICENSE
lmcache_vllm-0.6.2.3.dist-info/METADATA
lmcache_vllm-0.6.2.3.dist-info/WHEEL
lmcache_vllm-0.6.2.3.dist-info/entry_points.txt
lmcache_vllm-0.6.2.3.dist-info/top_level.txt
lmcache_vllm-0.6.2.3.dist-info/RECORD
