Metadata-Version: 2.1
Name: lmcache_vllm
Version: 0.6.2.3
Summary: lmcache_vllm: LMCache's wrapper for vllm
Author: LMCache team
Author-email: lmcacheteam@gmail.com
License-File: LICENSE
Requires-Dist: lmcache>=0.1.4
Requires-Dist: vllm<=0.6.2,>=0.6.1.post2
